g2p_nb/__init__.py
g2p_nb/evaluate.py
g2p_nb/predict.py
g2p_nb/stats.py
g2p_nb-0.1.1.dist-info/LICENSE
g2p_nb-0.1.1.dist-info/METADATA
g2p_nb-0.1.1.dist-info/WHEEL
g2p_nb-0.1.1.dist-info/RECORD
