Metadata-Version: 2.1
Name: g2p_nb
Version: 0.1.1
Summary: Grapheme-to-phoneme models for Norwegian bokmål to dialectal phonemic transcriptions
License: CC0 1.0 Deed
Author: Ingerid Dale
Author-email: ingerid.dale@nb.no
Requires-Python: >=3.10,<4.0
Classifier: License :: Other/Proprietary License
Classifier: Programming Language :: Python :: 3
Classifier: Programming Language :: Python :: 3.10
Classifier: Programming Language :: Python :: 3.11
Classifier: Programming Language :: Python :: 3.12
Requires-Dist: Levenshtein (>=0.25.1,<0.26.0)
Requires-Dist: convert-pa (>=0.1.0,<0.2.0)
Requires-Dist: google-cloud-storage (>=2.16.0,<3.0.0)
Requires-Dist: phonetisaurus (>=0.3.0,<0.4.0)
